Metadata-Version: 1.1
Name: annoy-fixed
Version: 1.16.3
Summary: fixed annoy bugs personer
Home-page: https://github.com/spotify/annoy
Author: Erik Bernhardsson
Author-email: mail@erikbern.com
License: Apache License 2.0
Keywords: nns,approximate nearest neighbor search
Platform: UNKNOWN
Classifier: Development Status :: 5 - Production/Stable
Classifier: Programming Language :: Python
Classifier: Programming Language :: Python :: 2.6
Classifier: Programming Language :: Python :: 2.7
Classifier: Programming Language :: Python :: 3.3
Classifier: Programming Language :: Python :: 3.4
Classifier: Programming Language :: Python :: 3.5
Classifier: Programming Language :: Python :: 3.6
